{"title":"Pinterest Starts Rolling Out Buyable Pins On Android Phones","description":"<img width=\"680\" height=\"465\" src=\"https://tctechcrunch2011.files.wordpress.com/2015/11/the-pinterest-shop.jpg?w=680\" class=\"attachment-large wp-post-image\" alt=\"The Pinterest Shop\" />&nbsp;Pinterest is starting to roll out Buyable Pins on Android phones today, the company said. Buyable Pins let some retailers who are partners with Pinterest and retailers use Shopify and Demandware. The company unveiled Buyable Pins earlier in June earlier this year, with the iPhone getting access to them later that month. The tool lets retailers add a buy button to pins that let users&hellip; <a href=\"http://techcrunch.com/2015/11/03/pinterest-starts-rolling-out-buyable-pins-on-android-devices/?ncid=rss\">Read More</a><img src=\"http://feeds.feedburner.com/~r/techcrunch/social/~4/-1hhxbhMRoM\" height=\"1\" width=\"1\" alt=\"\"/>","summary":"<img width=\"680\" height=\"465\" src=\"https://tctechcrunch2011.files.wordpress.com/2015/11/the-pinterest-shop.jpg?w=680\" class=\"attachment-large wp-post-image\" alt=\"The Pinterest Shop\" />&nbsp;Pinterest is starting to roll out Buyable Pins on Android phones today, the company said. Buyable Pins let some retailers who are partners with Pinterest and retailers use Shopify and Demandware. The company unveiled Buyable Pins earlier in June earlier this year, with the iPhone getting access to them later that month. The tool lets retailers add a buy button to pins that let users&hellip; <a href=\"http://techcrunch.com/2015/11/03/pinterest-starts-rolling-out-buyable-pins-on-android-devices/?ncid=rss\">Read More</a><img src=\"http://feeds.feedburner.com/~r/techcrunch/social/~4/-1hhxbhMRoM\" height=\"1\" width=\"1\" alt=\"\"/>","date":"2015-11-03T18:00:47.000Z","pubdate":"2015-11-03T18:00:47.000Z","pubDate":"2015-11-03T18:00:47.000Z","link":"http://feedproxy.google.com/~r/techcrunch/social/~3/-1hhxbhMRoM/","guid":"http://techcrunch.com/?p=1232437","author":"Matthew Lynley","comments":"http://techcrunch.com/2015/11/03/pinterest-starts-rolling-out-buyable-pins-on-android-devices/#comments","origlink":"http://techcrunch.com/2015/11/03/pinterest-starts-rolling-out-buyable-pins-on-android-devices/?ncid=rss","image":{"url":"https://tctechcrunch2011.files.wordpress.com/2015/11/the-pinterest-shop.jpg?w=210&h=158&crop=1"},"source":{},"categories":["Apps","Mobile","Social","Startups","TC","Pinterest","buyable pins"]}