{"title":"Oklahoma City, Jacksonville And Tampa Invited To Explore Google Fiber","description":"<img width=\"680\" height=\"468\" src=\"https://tctechcrunch2011.files.wordpress.com/2015/10/fiberexpansionmap_oct2015.png?w=680\" class=\"attachment-large wp-post-image\" alt=\"FiberExpansionMap_Oct2015\" />&nbsp;Forget that Google Fiber went down in Kansas City during the World Series last night, the service is speedy as all hell.\r\nToday, the Fiber team announced the exploration of 3 new locations: Oklahoma City, Jacksonville and Tampa:\r\nWe&#8217;re inviting Oklahoma City, OK, Jacksonville, FL and Tampa, FL, to explore bringing Google Fiber to their communities, as we did last month with three other cities. <a href=\"http://techcrunch.com/2015/10/28/oklahoma-city-jacksonville-and-tampa-invited-to-explore-google-fiber/?ncid=rss\">Read More</a><div class=\"feedflare\">\r\n<a href=\"http://feeds.feedburner.com/~ff/crunchgear?a=lHg9vGYt44I:UtpJLlUDNzo:V_sGLiPBpWU\"><img src=\"http://feeds.feedburner.com/~ff/crunchgear?i=lHg9vGYt44I:UtpJLlUDNzo:V_sGLiPBpWU\" border=\"0\"></img></a> <a href=\"http://feeds.feedburner.com/~ff/crunchgear?a=lHg9vGYt44I:UtpJLlUDNzo:F7zBnMyn0Lo\"><img src=\"http://feeds.feedburner.com/~ff/crunchgear?i=lHg9vGYt44I:UtpJLlUDNzo:F7zBnMyn0Lo\" border=\"0\"></img></a> <a href=\"http://feeds.feedburner.com/~ff/crunchgear?a=lHg9vGYt44I:UtpJLlUDNzo:yIl2AUoC8zA\"><img src=\"http://feeds.feedburner.com/~ff/crunchgear?d=yIl2AUoC8zA\" border=\"0\"></img></a>\r\n</div>","summary":"<img width=\"680\" height=\"468\" src=\"https://tctechcrunch2011.files.wordpress.com/2015/10/fiberexpansionmap_oct2015.png?w=680\" class=\"attachment-large wp-post-image\" alt=\"FiberExpansionMap_Oct2015\" />&nbsp;Forget that Google Fiber went down in Kansas City during the World Series last night, the service is speedy as all hell.\r\nToday, the Fiber team announced the exploration of 3 new locations: Oklahoma City, Jacksonville and Tampa:\r\nWe&#8217;re inviting Oklahoma City, OK, Jacksonville, FL and Tampa, FL, to explore bringing Google Fiber to their communities, as we did last month with three other cities. <a href=\"http://techcrunch.com/2015/10/28/oklahoma-city-jacksonville-and-tampa-invited-to-explore-google-fiber/?ncid=rss\">Read More</a><div class=\"feedflare\">\r\n<a href=\"http://feeds.feedburner.com/~ff/crunchgear?a=lHg9vGYt44I:UtpJLlUDNzo:V_sGLiPBpWU\"><img src=\"http://feeds.feedburner.com/~ff/crunchgear?i=lHg9vGYt44I:UtpJLlUDNzo:V_sGLiPBpWU\" border=\"0\"></img></a> <a href=\"http://feeds.feedburner.com/~ff/crunchgear?a=lHg9vGYt44I:UtpJLlUDNzo:F7zBnMyn0Lo\"><img src=\"http://feeds.feedburner.com/~ff/crunchgear?i=lHg9vGYt44I:UtpJLlUDNzo:F7zBnMyn0Lo\" border=\"0\"></img></a> <a href=\"http://feeds.feedburner.com/~ff/crunchgear?a=lHg9vGYt44I:UtpJLlUDNzo:yIl2AUoC8zA\"><img src=\"http://feeds.feedburner.com/~ff/crunchgear?d=yIl2AUoC8zA\" border=\"0\"></img></a>\r\n</div>","date":"2015-10-28T20:14:05.000Z","pubdate":"2015-10-28T20:14:05.000Z","pubDate":"2015-10-28T20:14:05.000Z","link":"http://techcrunch.com/2015/10/28/oklahoma-city-jacksonville-and-tampa-invited-to-explore-google-fiber/?ncid=rss","guid":"http://techcrunch.com/?p=1230253","author":"Drew Olanoff","comments":"http://techcrunch.com/2015/10/28/oklahoma-city-jacksonville-and-tampa-invited-to-explore-google-fiber/#comments","origlink":null,"image":{"url":"https://tctechcrunch2011.files.wordpress.com/2015/10/fiberexpansionmap_oct2015.png?w=210&h=158&crop=1"},"source":{},"categories":["Developer","Gadgets","Government","Media","broadband","google fiber","Google","Fiber","Kansas City","kansas city kansas"]}