{"title":"Vinod Khosla Steps Off Square’s Board In Advance Of Its IPO","description":"<img width=\"680\" height=\"453\" src=\"https://tctechcrunch2011.files.wordpress.com/2015/09/vinod-khosla-10.jpg?w=680\" class=\"attachment-large wp-post-image\" alt=\"Vinod Khosla - 10\" />&nbsp;Vinod Khosla has stepped down as a director of the San Francisco-based payments company Square as it prepares to go public.\r\nMedia outlets Business Insider and Forbes reported on the news earlier today, citing an amended SEC statement. <a href=\"http://techcrunch.com/2015/10/26/vinod-khosla-steps-off-squares-board-in-advance-of-its-ipo/?ncid=rss\">Read More</a><img src=\"http://feeds.feedburner.com/~r/techcrunch/startups/~4/ku1qiK3yPgE\" height=\"1\" width=\"1\" alt=\"\"/>","summary":"<img width=\"680\" height=\"453\" src=\"https://tctechcrunch2011.files.wordpress.com/2015/09/vinod-khosla-10.jpg?w=680\" class=\"attachment-large wp-post-image\" alt=\"Vinod Khosla - 10\" />&nbsp;Vinod Khosla has stepped down as a director of the San Francisco-based payments company Square as it prepares to go public.\r\nMedia outlets Business Insider and Forbes reported on the news earlier today, citing an amended SEC statement. <a href=\"http://techcrunch.com/2015/10/26/vinod-khosla-steps-off-squares-board-in-advance-of-its-ipo/?ncid=rss\">Read More</a><img src=\"http://feeds.feedburner.com/~r/techcrunch/startups/~4/ku1qiK3yPgE\" height=\"1\" width=\"1\" alt=\"\"/>","date":"2015-10-26T19:38:50.000Z","pubdate":"2015-10-26T19:38:50.000Z","pubDate":"2015-10-26T19:38:50.000Z","link":"http://feedproxy.google.com/~r/techcrunch/startups/~3/ku1qiK3yPgE/","guid":"http://techcrunch.com/?p=1229093","author":"Connie Loizos","comments":"http://techcrunch.com/2015/10/26/vinod-khosla-steps-off-squares-board-in-advance-of-its-ipo/#comments","origlink":"http://techcrunch.com/2015/10/26/vinod-khosla-steps-off-squares-board-in-advance-of-its-ipo/?ncid=rss","image":{"url":"https://tctechcrunch2011.files.wordpress.com/2015/09/vinod-khosla-10.jpg?w=210&h=158&crop=1"},"source":{},"categories":["Startups","TC","Venture Capital","Vinod Khosla","Square","kholsa ventures"]}